napool/__init__.py
napool/napool.py
napool-0.0.2.dist-info/METADATA
napool-0.0.2.dist-info/WHEEL
napool-0.0.2.dist-info/licenses/LICENSE
napool-0.0.2.dist-info/RECORD
